odoo/addons/account_payment_line/README.rst
odoo/addons/account_payment_line/__init__.py
odoo/addons/account_payment_line/__manifest__.py
odoo/addons/account_payment_line/hooks.py
odoo/addons/account_payment_line/i18n/account_payment_line.pot
odoo/addons/account_payment_line/i18n/it.po
odoo/addons/account_payment_line/models/__init__.py
odoo/addons/account_payment_line/models/account_move.py
odoo/addons/account_payment_line/models/account_payment.py
odoo/addons/account_payment_line/models/counterpart_line.py
odoo/addons/account_payment_line/readme/CONTRIBUTORS.rst
odoo/addons/account_payment_line/readme/DESCRIPTION.rst
odoo/addons/account_payment_line/readme/USAGE.rst
odoo/addons/account_payment_line/security/ir.model.access.csv
odoo/addons/account_payment_line/static/description/icon.png
odoo/addons/account_payment_line/static/description/index.html
odoo/addons/account_payment_line/tests/__init__.py
odoo/addons/account_payment_line/tests/test_account_payment_line.py
odoo/addons/account_payment_line/views/account_payment_views.xml
odoo_addon_account_payment_line-16.0.1.0.1.1.dist-info/METADATA
odoo_addon_account_payment_line-16.0.1.0.1.1.dist-info/WHEEL
odoo_addon_account_payment_line-16.0.1.0.1.1.dist-info/top_level.txt
odoo_addon_account_payment_line-16.0.1.0.1.1.dist-info/RECORD
